emojipasta/__init__.py
emojipasta/generator.py
emojipasta/data/__init__.py
emojipasta/data/emoji_mappings.py
emojipasta/util/__init__.py
emojipasta/util/emojify.py
emojipasta/util/text.py
emojipasta-1.0.dist-info/METADATA
emojipasta-1.0.dist-info/WHEEL
emojipasta-1.0.dist-info/licenses/LICENSE
emojipasta-1.0.dist-info/RECORD
