Metadata-Version: 2.1
Name: emojipasta
Version: 1.0
Summary: emojipasta is a module for emojifying text
Project-URL: homepage, https://github.com/SilasStokes/emojipasta
Project-URL: repository, https://github.com/SilasStokes/emojipasta
Author: Kevinpgalligan, MakufonSkifto
Author-email: Silas Stokes <stokessilas@gmail.com>
License-Expression: MIT
License-File: LICENSE
Keywords: emoji,emojifier,emojify,emojifyer,emojipasta,emojis,pasta,reddit
Requires-Python: >=3.5
Requires-Dist: emoji<3.0.0,>=2.0.0
